pytest_capture_warnings/__init__.py
pytest_capture_warnings-0.0.4.dist-info/LICENSE
pytest_capture_warnings-0.0.4.dist-info/METADATA
pytest_capture_warnings-0.0.4.dist-info/WHEEL
pytest_capture_warnings-0.0.4.dist-info/entry_points.txt
pytest_capture_warnings-0.0.4.dist-info/top_level.txt
pytest_capture_warnings-0.0.4.dist-info/RECORD
