Metadata-Version: 2.1
Name: pytest-capture-warnings
Version: 0.0.4
Summary: pytest plugin to capture all warnings and put them in one file of your choice
Home-page: https://github.com/athinkingape/pytest-capture-warnings
License: MIT
Platform: UNKNOWN
License-File: LICENSE
Requires-Dist: pytest
Requires-Dist: importlib-metadata
